premise_gwp/__init__.py
premise_gwp/biosphere.py
premise_gwp/version.py
premise_gwp/data/lcia_gwp2021_100a.xlsx
premise_gwp/data/lcia_gwp2021_100a_w_bio.xlsx
premise_gwp/data/lcia_gwp2021_20a.xlsx
premise_gwp/data/lcia_gwp2021_20a_w_bio.xlsx
premise_gwp/data/lcia_gwp_100a.xlsx
premise_gwp/data/lcia_gwp_100a_w_bio.xlsx
premise_gwp/data/lcia_gwp_20a.xlsx
premise_gwp/data/lcia_gwp_20a_w_bio.xlsx
premise_gwp/data/mapping_ei310.yaml
premise_gwp-0.9.8.dist-info/licenses/LICENSE
premise_gwp-0.9.8.dist-info/METADATA
premise_gwp-0.9.8.dist-info/WHEEL
premise_gwp-0.9.8.dist-info/top_level.txt
premise_gwp-0.9.8.dist-info/RECORD
