Metadata-Version: 2.4
Name: premise_gwp
Version: 0.9.8
Summary: Import IPCC's GWP100a method, with biogenic CO2 CFs, into Brightway2
Author-email: Romain Sacchi <romain.sacchi@psi.ch>
License: BSD-3-Clause
Project-URL: Homepage, https://github.com/romainsacchi/premise_gwp
Project-URL: Repository, https://github.com/romainsacchi/premise_gwp
Classifier: Intended Audience :: End Users/Desktop
Classifier: Intended Audience :: Developers
Classifier: Intended Audience :: Science/Research
Classifier: License :: OSI Approved :: BSD License
Classifier: Operating System :: MacOS :: MacOS X
Classifier: Operating System :: Microsoft :: Windows
Classifier: Operating System :: POSIX
Classifier: Programming Language :: Python
Classifier: Programming Language :: Python :: 3
Classifier: Programming Language :: Python :: 3.5
Classifier: Programming Language :: Python :: 3.6
Classifier: Programming Language :: Python :: 3.7
License-File: LICENSE
Requires-Dist: bw2io
Requires-Dist: bw2data
Requires-Dist: requests
Requires-Dist: pyyaml
Requires-Dist: numpy<2.0.0
Dynamic: license-file
